gingerai/ModelExecutor.py
gingerai/ModelUploader.py
gingerai/__init__.py
gingerai/executor.py
gingerai-0.2.0.dist-info/METADATA
gingerai-0.2.0.dist-info/WHEEL
gingerai-0.2.0.dist-info/top_level.txt
gingerai-0.2.0.dist-info/RECORD
