Metadata-Version: 2.1
Name: gingerai
Version: 0.2.0
Summary: Ginger AI Python Library
Home-page: https://github.com/ginger-ai
Classifier: Programming Language :: Python :: 3
Classifier: License :: OSI Approved :: MIT License
Classifier: Operating System :: OS Independent
Requires-Python: >=3.6
Requires-Dist: torch
Requires-Dist: torchsummary
Requires-Dist: numpy
Requires-Dist: requests
Requires-Dist: tqdm
Requires-Dist: grequests
Requires-Dist: joblib
